waao/__init__.py
waao/conversion.py
waao/disp.py
waao/fileops.py
waao/search.py
waao-0.1.dist-info/licenses/LICENSE.md
waao-0.1.dist-info/METADATA
waao-0.1.dist-info/WHEEL
waao-0.1.dist-info/entry_points.txt
waao-0.1.dist-info/top_level.txt
waao-0.1.dist-info/RECORD
