Metadata-Version: 2.4
Name: waao
Version: 0.1
Summary: A Python utility package for file operations including conversions, searching, displaying, and file management
Home-page: https://github.com/manu-waao/waao
Author: manu-waao
Author-email: manukumar4648@gmail.com
Classifier: Programming Language :: Python :: 3
Classifier: License :: OSI Approved :: MIT License
Classifier: Operating System :: OS Independent
Requires-Python: >=3.11
License-File: LICENSE.md
Requires-Dist: fpdf
Requires-Dist: Pillow
Requires-Dist: python-docx
Requires-Dist: PyPDF2
Dynamic: author
Dynamic: author-email
Dynamic: classifier
Dynamic: description
Dynamic: description-content-type
Dynamic: home-page
Dynamic: license-file
Dynamic: requires-dist
Dynamic: requires-python
Dynamic: summary
